{"created_at": "Fri Feb 09 20:17:40 +0000 2018", "hashtags": [{"text": "\u0531\u0576\u056f\u0578\u0582\u0574"}, {"text": "\u0586\u056b\u056c\u0574"}, {"text": "\u057a\u0580\u0565\u0574\u056b\u0565\u0580\u0561"}], "id": 962057934740930563, "id_str": "962057934740930563", "lang": "hy", "possibly_sensitive": true, "source": "<a href=\"http://instagram.com\" rel=\"nofollow\">Instagram</a>", "text": "#\u0531\u0576\u056f\u0578\u0582\u0574 #\u0586\u056b\u056c\u0574 #\u057a\u0580\u0565\u0574\u056b\u0565\u0580\u0561\n\u0534\u056b\u057f\u0565\u0584\u055d\u0574\u056b\u057b\u0587 \u0583\u0565\u057f\u0580\u057e\u0561\u0580\u056b 13-\u0568 \u056a\u0561\u0574\u0568\u055d 18:30, \u056b\u057d\u056f \u0583\u0565\u057f\u0580\u057e\u0561\u0580\u056b 14-\u056b\u0581 \u056a\u0561\u0574\u0568\u055d 14:30\u2026 https://t.co/KO08BKnXrm", "urls": [{"expanded_url": "https://www.instagram.com/p/Be_TJwwgFQA/", "url": "https://t.co/KO08BKnXrm"}], "user": {"created_at": "Wed Jul 27 06:21:26 +0000 2011", "default_profile": true, "description": "\u041f\u0440\u043e\u0434\u044e\u0441\u0435\u0440 . \u0420\u0435\u0436\u0438\u0441\u0441\u0435\u0440 . \u0410\u043a\u0442\u0435\u0440. +374-96-02-55-50.+374-55-23-55-50.+37494245550", "favourites_count": 139, "followers_count": 139, "friends_count": 1109, "geo_enabled": true, "id": 343201912, "lang": "ru", "listed_count": 1, "location": "Armenia", "name": "#GAGIK #ATASYAN", "profile_background_color": "C0DEED", "profile_background_image_url": "http://abs.twimg.com/images/themes/theme1/bg.png", "profile_banner_url": "https://pbs.twimg.com/profile_banners/343201912/1501308989", "profile_image_url": "http://pbs.twimg.com/profile_images/914182904351281157/BDgLebAW_normal.jpg", "profile_link_color": "1DA1F2", "profile_sidebar_fill_color": "DDEEF6", "profile_text_color": "333333", "screen_name": "GAGIKATASYAN", "statuses_count": 3143, "time_zone": "Central Time (US & Canada)", "utc_offset": -21600}, "user_mentions": []}
